cyctp/LICENSE.txt
cyctp/ctp_handler.py
cyctp/ctp_market.so
cyctp/ctp_struct.py
cyctp/ctp_trader.so
cyctp/__init__.py
cyctp/lib/thostmduserapi.dll
cyctp/lib/thosttraderapi.dll
cyctp/lib/thosttraderapi.lib
cyctp/lib/libthostmduserapi.so
cyctp/lib/libthosttraderapi.so
cyctp/lib/thostmduserapi.lib
cyctp-1.0.2.dist-info/RECORD
cyctp-1.0.2.dist-info/top_level.txt
cyctp-1.0.2.dist-info/METADATA
cyctp-1.0.2.dist-info/DESCRIPTION.rst
cyctp-1.0.2.dist-info/metadata.json
cyctp-1.0.2.dist-info/WHEEL
