Metadata-Version: 2.0
Name: cyctp
Version: 1.0.2
Summary: Cython wrapper for CTP
Home-page: https://github.com/xushenkun/cyctp
Author: Xu Shenkun
Author-email: xsk1983@126.com
License: MIT
Download-URL: https://github.com/xushenkun/cyctp/releases
Keywords: cython ctp trade market stock
Platform: UNKNOWN
Requires-Dist: cython
